cvpal/__init__.py
cvpal/generate/__init__.py
cvpal/generate/classification_dataset.py
cvpal/generate/detection_dataset.py
cvpal/preprocessing/__init__.py
cvpal/preprocessing/images_detection.py
cvpal/preprocessing/different_format_utils/__init__.py
cvpal/preprocessing/different_format_utils/coco_json_implementation_functions.py
cvpal/preprocessing/different_format_utils/createml_json_implementation_functions.py
cvpal/preprocessing/different_format_utils/darknet_txt_implementation_functions.py
cvpal/preprocessing/different_format_utils/paligemma_jsonal_implementation_functions.py
cvpal/preprocessing/different_format_utils/tf_record_implementation_functions.py
cvpal/preprocessing/different_format_utils/txt_implementation_functions.py
cvpal/preprocessing/different_format_utils/xml_implementation_functions.py
tests/__init__.py
cvpal-1.0.2.dist-info/LICENSE.txt
cvpal-1.0.2.dist-info/METADATA
cvpal-1.0.2.dist-info/WHEEL
cvpal-1.0.2.dist-info/top_level.txt
cvpal-1.0.2.dist-info/RECORD
