Metadata-Version: 2.1
Name: cvpal
Version: 1.0.2
Summary: A Python library for every Computer Vision Engineer
Author: Mohamed E. Ibrahim
Author-email: mohamedelsayed3487@gmail.com
Keywords: python,computer vision,cv,Data Reformatting,YOLO,Roboflow,ultralytics,Data preprocessing
Classifier: Development Status :: 1 - Planning
Classifier: Intended Audience :: Developers
Classifier: Programming Language :: Python :: 3
Classifier: Operating System :: Unix
Classifier: Operating System :: MacOS :: MacOS X
Classifier: Operating System :: Microsoft :: Windows
License-File: LICENSE.txt
Requires-Dist: pandas
Requires-Dist: pyaml
Requires-Dist: PyYAML
Requires-Dist: python-dateutil
Requires-Dist: numpy
Requires-Dist: diffusers
Requires-Dist: matplotlib
Requires-Dist: pillow
Requires-Dist: torch
Requires-Dist: openai
Requires-Dist: tzdata
Requires-Dist: six
